{"stats":{"minecraft:killed":{"minecraft:villager":5},"minecraft:killed_by":{"minecraft:player":23},"minecraft:mined":{"minecraft:grass_block":14,"minecraft:spruce_sapling":399,"minecraft:fire":1,"minecraft:tall_grass":1,"minecraft:tnt":2,"minecraft:grass":10,"minecraft:oak_log":50,"minecraft:dirt":94,"minecraft:oak_leaves":6},"minecraft:picked_up":{"minecraft:magenta_glazed_terracotta":1,"minecraft:wheat":11,"minecraft:azure_bluet":2,"minecraft:splash_potion":3,"minecraft:leather_leggings":1,"minecraft:lead":2,"minecraft:string":2,"minecraft:red_bed":4,"minecraft:soul_soil":64,"minecraft:sticky_piston":64,"minecraft:iron_leggings":1,"minecraft:armor_stand":1,"minecraft:smooth_stone":8,"minecraft:light_weighted_pressure_plate":64,"minecraft:beef":2,"minecraft:poppy":1,"minecraft:smooth_quartz":1,"minecraft:light_gray_wool":1,"minecraft:smooth_quartz_stairs":1,"minecraft:golden_helmet":2,"minecraft:stick":7,"minecraft:end_stone":76,"minecraft:acacia_log":128,"minecraft:tnt":770,"minecraft:arrow":1,"minecraft:diamond_chestplate":1,"minecraft:oak_chest_boat":2,"minecraft:totem_of_undying":1,"minecraft:netherite_chestplate":18,"minecraft:white_wool":1,"minecraft:oxeye_daisy":2,"minecraft:netherite_boots":1,"minecraft:leather_chestplate":1,"minecraft:feather":1,"minecraft:chiseled_bookshelf":192,"minecraft:leather":2,"minecraft:oak_log":55,"minecraft:netherite_leggings":1,"minecraft:dirt":657,"minecraft:lantern":1,"minecraft:leather_boots":1,"minecraft:wheat_seeds":15,"minecraft:iron_ingot":3,"minecraft:music_disc_far":1,"minecraft:oak_planks":2,"minecraft:dandelion":11,"minecraft:dropper":64,"minecraft:sand":197,"minecraft:trapped_chest":64,"minecraft:spruce_sapling":127,"minecraft:netherite_helmet":1,"minecraft:iron_helmet":1,"minecraft:stripped_jungle_wood":1,"minecraft:painting":1,"minecraft:chainmail_helmet":1,"minecraft:oak_sapling":5},"minecraft:dropped":{"minecraft:iron_ingot":3,"minecraft:daylight_detector":64,"minecraft:stripped_spruce_log":64,"minecraft:wheat_seeds":5,"minecraft:oak_pressure_plate":64,"minecraft:oak_log":64,"minecraft:polished_blackstone":1,"minecraft:diamond":5,"minecraft:netherite_chestplate":5,"minecraft:lead":1,"minecraft:jungle_wood":128,"minecraft:chiseled_bookshelf":384,"minecraft:spruce_stairs":64,"minecraft:acacia_log":128,"minecraft:grass_block":2,"minecraft:light_weighted_pressure_plate":192,"minecraft:dirt":261,"minecraft:snowball":41,"minecraft:stripped_birch_log":64,"minecraft:oak_stairs":128,"minecraft:writable_book":2,"minecraft:sand":80,"minecraft:stripped_oak_wood":128,"minecraft:trapped_chest":128,"minecraft:white_wool":1,"minecraft:birch_stairs":64,"minecraft:gray_carpet":64,"minecraft:redstone_block":64,"minecraft:dandelion":3,"minecraft:oak_door":64,"minecraft:soul_soil":64,"minecraft:stripped_jungle_wood":1,"minecraft:sticky_piston":128,"minecraft:diamond_hoe":6,"minecraft:wheat":1,"minecraft:blue_wool":64,"minecraft:light_gray_wool":1,"minecraft:oak_planks":256,"minecraft:slime_block":64,"minecraft:end_stone":21,"minecraft:warped_door":64,"minecraft:spruce_fence":64,"minecraft:birch_fence_gate":64,"minecraft:lightning_rod":640,"minecraft:flint_and_steel":1,"minecraft:oak_chest_boat":1,"minecraft:oak_button":192,"minecraft:spruce_trapdoor":256,"minecraft:orange_terracotta":1,"minecraft:oak_wood":64,"minecraft:dropper":192,"minecraft:warped_fence":128,"minecraft:quartz_block":1,"minecraft:pink_wool":64,"minecraft:jungle_log":320,"minecraft:birch_door":64,"minecraft:oak_sapling":2,"minecraft:redstone_torch":64,"minecraft:spruce_wood":64,"minecraft:spruce_slab":64,"minecraft:spruce_log":576,"minecraft:birch_button":128},"minecraft:used":{"minecraft:oak_trapdoor":14,"minecraft:oak_fence":6,"minecraft:trident":34,"minecraft:light_blue_banner":4,"minecraft:netherite_sword":13,"minecraft:iron_shovel":11,"minecraft:orange_concrete":12,"minecraft:flint_and_steel":32,"minecraft:smooth_quartz_slab":3,"minecraft:armor_stand":10,"minecraft:red_concrete":675,"minecraft:spruce_slab":60,"minecraft:polished_blackstone":360,"minecraft:diamond_hoe":1890,"minecraft:ladder":240,"minecraft:oak_sign":12,"minecraft:polished_basalt":107,"minecraft:spruce_planks":34,"minecraft:donkey_spawn_egg":5,"minecraft:white_terracotta":167,"minecraft:stone":37,"minecraft:stripped_jungle_wood":14,"minecraft:bell":1,"minecraft:green_terracotta":43,"minecraft:iron_chestplate":1,"minecraft:orange_stained_glass":33,"minecraft:torch":11,"minecraft:dragon_egg":16,"minecraft:soul_sand":8,"minecraft:dirt":1996,"minecraft:anvil":4,"minecraft:brick_slab":602,"minecraft:jungle_planks":16,"minecraft:yellow_carpet":5,"minecraft:spruce_fence":65,"minecraft:blue_concrete":11,"minecraft:snowball":23,"minecraft:milk_bucket":7,"minecraft:andesite_wall":5,"minecraft:warden_spawn_egg":1,"minecraft:glow_squid_spawn_egg":38,"minecraft:frog_spawn_egg":4,"minecraft:mossy_cobblestone_stairs":33,"minecraft:stone_brick_slab":37,"minecraft:brown_terracotta":15,"minecraft:sea_lantern":2,"minecraft:bricks":383,"minecraft:quartz_pillar":117,"minecraft:villager_spawn_egg":6,"minecraft:light_weighted_pressure_plate":13,"minecraft:quartz_slab":58,"minecraft:grass_block":165,"minecraft:lantern":20,"minecraft:iron_axe":65,"minecraft:spruce_button":12,"minecraft:slime_block":17,"minecraft:warped_fence":1,"minecraft:brick_stairs":70,"minecraft:spawner":7,"minecraft:copper_ore":2,"minecraft:wet_sponge":7,"minecraft:iron_helmet":1,"minecraft:tropical_fish_spawn_egg":22,"minecraft:iron_boots":1,"minecraft:smooth_quartz":11,"minecraft:barrel":16,"minecraft:item_frame":10,"minecraft:yellow_concrete_powder":1,"minecraft:light_gray_wool":12,"minecraft:diamond_chestplate":2,"minecraft:bow":175,"minecraft:lime_concrete":19,"minecraft:sniffer_spawn_egg":1,"minecraft:emerald_block":29,"minecraft:magenta_wool":11,"minecraft:tall_grass":168,"minecraft:written_book":3,"minecraft:furnace":20,"minecraft:oak_sapling":647,"minecraft:gold_block":699,"minecraft:skeleton_skull":5,"minecraft:dragon_head":4,"minecraft:observer":2,"minecraft:orange_terracotta":251,"minecraft:iron_leggings":1,"minecraft:pointed_dripstone":6,"minecraft:quartz_bricks":734,"minecraft:wheat_seeds":1390,"minecraft:water_bucket":163,"minecraft:tube_coral_block":10,"minecraft:cobblestone_stairs":70,"minecraft:light_blue_glazed_terracotta":2,"minecraft:spruce_door":1,"minecraft:lodestone":19,"minecraft:snow_block":12,"minecraft:birch_planks":12,"minecraft:lead":3,"minecraft:red_nether_bricks":31,"minecraft:lime_wool":8,"minecraft:oak_planks":83,"minecraft:iron_golem_spawn_egg":1,"minecraft:sandstone":6,"minecraft:composter":9,"minecraft:sheep_spawn_egg":102,"minecraft:chiseled_nether_bricks":10,"minecraft:oak_leaves":367,"minecraft:smooth_quartz_stairs":8,"minecraft:dark_oak_trapdoor":4,"minecraft:stripped_mangrove_wood":11,"minecraft:mossy_cobblestone":60,"minecraft:diamond_block":42,"minecraft:lime_terracotta":69,"minecraft:terracotta":27,"minecraft:yellow_terracotta":1463,"minecraft:strider_spawn_egg":8,"minecraft:light_blue_concrete":9,"minecraft:tnt":32,"minecraft:crafting_table":1,"minecraft:red_bed":70,"minecraft:phantom_spawn_egg":14,"minecraft:blue_ice":10,"minecraft:painting":31,"minecraft:stone_brick_wall":2,"minecraft:gray_concrete":245,"minecraft:stripped_cherry_wood":6,"minecraft:endermite_spawn_egg":2,"minecraft:end_stone":373,"minecraft:spruce_log":104,"minecraft:dark_oak_door":2,"minecraft:oak_log":4,"minecraft:sticky_piston":4,"minecraft:black_terracotta":231,"minecraft:blue_glazed_terracotta":24,"minecraft:red_sandstone":541,"minecraft:black_wool":55,"minecraft:black_concrete":238,"minecraft:waxed_exposed_cut_copper_stairs":9,"minecraft:daylight_detector":2,"minecraft:crying_obsidian":16,"minecraft:stripped_jungle_log":9,"minecraft:light_gray_concrete":268,"minecraft:brown_wool":3,"minecraft:pig_spawn_egg":56,"minecraft:lectern":5,"minecraft:cyan_concrete":52,"minecraft:oak_pressure_plate":13,"minecraft:iron_door":5,"minecraft:spruce_sapling":1410,"minecraft:cut_red_sandstone":6,"minecraft:flowering_azalea_leaves":6,"minecraft:polished_andesite_slab":5,"minecraft:yellow_wool":5,"minecraft:golden_helmet":2,"minecraft:stone_axe":63,"minecraft:fishing_rod":25,"minecraft:light_blue_concrete_powder":36,"minecraft:cobblestone":498,"minecraft:stripped_crimson_hyphae":11,"minecraft:grindstone":1,"minecraft:dark_oak_fence":49,"minecraft:lapis_block":19,"minecraft:bucket":2,"minecraft:chain":4,"minecraft:glass_pane":38,"minecraft:magenta_glazed_terracotta":9,"minecraft:sea_pickle":10,"minecraft:bamboo_mosaic_slab":9,"minecraft:white_concrete":419,"minecraft:candle":19,"minecraft:kelp":7,"minecraft:oak_hanging_sign":1,"minecraft:splash_potion":2,"minecraft:smooth_stone":84,"minecraft:bone_meal":67,"minecraft:purple_wool":14},"minecraft:custom":{"minecraft:interact_with_anvil":4,"minecraft:mob_kills":5,"minecraft:interact_with_crafting_table":13,"minecraft:open_barrel":1,"minecraft:bell_ring":6,"minecraft:leave_game":9,"minecraft:time_since_death":32033,"minecraft:climb_one_cm":35006,"minecraft:sprint_one_cm":539873,"minecraft:walk_one_cm":750047,"minecraft:drop":138,"minecraft:talked_to_villager":1,"minecraft:play_time":680283,"minecraft:deaths":41,"minecraft:sneak_time":35586,"minecraft:walk_under_water_one_cm":7792,"minecraft:interact_with_lectern":4,"minecraft:jump":5915,"minecraft:walk_on_water_one_cm":8632,"minecraft:total_world_time":680283,"minecraft:interact_with_furnace":5,"minecraft:interact_with_grindstone":3,"minecraft:sleep_in_bed":26,"minecraft:time_since_rest":32067,"minecraft:damage_taken":27077,"minecraft:damage_dealt":9003,"minecraft:swim_one_cm":46449,"minecraft:fly_one_cm":7356502,"minecraft:player_kills":19,"minecraft:open_chest":20,"minecraft:crouch_one_cm":67479,"minecraft:fall_one_cm":208759,"minecraft:horse_one_cm":32076},"minecraft:crafted":{"minecraft:oak_planks":300,"minecraft:diamond_hoe":6,"minecraft:iron_axe":1,"minecraft:ladder":240,"minecraft:crafting_table":1,"minecraft:stone_axe":1,"minecraft:stick":596,"minecraft:iron_shovel":1,"minecraft:diamond_chestplate":1}},"DataVersion":3465}